plantigo_common/__init__.py
plantigo_common/django/__init__.py
plantigo_common/django/proto_serializer.py
plantigo_common/python/__init__.py
plantigo_common/python/auth/__init__.py
plantigo_common/python/auth/token_service.py
plantigo_common/python/grpc/__init__.py
plantigo_common/python/grpc/auth_interceptor.py
plantigo_common/python/grpc/rpc_caller.py
plantigo_common-1.1.0.dist-info/METADATA
plantigo_common-1.1.0.dist-info/WHEEL
plantigo_common-1.1.0.dist-info/top_level.txt
plantigo_common-1.1.0.dist-info/RECORD
